{
    "title": "Violin Concerto No. 3 (Haydn)",
    "text": "The Violin Concerto No. 3 in A major (Hob. VIIa/3) (\"Melker Konzert\") was composed by Joseph Haydn probably between 1765 and 1770.\n\n\n== References ==\nNotes\nSourcesThomas, G\u00fcnter. Preface (PDF). Concerto for Violin and Orchestra A major Hob. VIIa:3. By Haydn, Joseph.  Lohmann, Heinz (ed.).  (in German, English, and French). G. Henle Verlag. Archived from the original (PDF) on 2011-07-18.\n\n\n== External links ==\nViolin Concerto No. 3: Scores at the International Music Score Library Project\nViolin Concerto in A major (\"Melker Konzert\"), H. 7a/3 at Answers.com",
    "link": "https://en.wikipedia.org/wiki/Violin_Concerto_No._3_(Haydn)",
    "summary": "The Violin Concerto No. 3 in A major (Hob. VIIa/3) (\"Melker Konzert\") was composed by Joseph Haydn probably between 1765 and 1770.\n\n",
    "section titles": "References External links",
    "keywords": ["Violin", "Concerto", "A", "major", "Joseph", "Haydn"]
}